Metadata-Version: 1.0
Name: AMB-distribution
Version: 0.1
Summary: Gaussian distributions
Home-page: UNKNOWN
Author: Andrew Paster
Author-email: abdelrahmanrefaat601@gmail.com
License: UNKNOWN
Platform: UNKNOWN
